MANIFEST.in
README.rst
setup.py
extra/git-checkout.txt
extra/jiver-completion.sh
extra/project-upgrade.txt
extra/upgrade-analyzer.jar
jiver/__init__.py
jiver/build_and_run.py
jiver/core_checkout.py
jiver/database.py
jiver/diffmerge.py
jiver/main.py
jiver/maven_utils.py
jiver/move_theme_to_top_level.py
jiver/overlay.py
jiver/tabs.py
jiver/upgrade_project.py
jiver/vpn.py
jiver.egg-info/PKG-INFO
jiver.egg-info/SOURCES.txt
jiver.egg-info/dependency_links.txt
jiver.egg-info/entry_points.txt
jiver.egg-info/requires.txt
jiver.egg-info/top_level.txt