Metadata-Version: 1.0
Name: jiver
Version: 0.1.28
Summary: Collection of utilities for a Jive PS engineer
Home-page: http://www.github.com/digitaldarwin/jiver
Author: Michael Masters
Author-email: mmasters+jiver@gmail.com
License: MIT License
Platform: UNKNOWN
Classifier: Development Status :: 4 - Beta
Classifier: Intended Audience :: Developers
Classifier: Natural Language :: English
Classifier: License :: OSI Approved :: MIT License
Classifier: Programming Language :: Python
Classifier: Programming Language :: Python :: 2.6
Classifier: Programming Language :: Python :: 2.7
